moadian2/__init__.py
moadian2/dto.py
moadian2/encryption.py
moadian2/main.py
moadian2/settings.py
moadian2-0.0.2.dist-info/LICENSE
moadian2-0.0.2.dist-info/METADATA
moadian2-0.0.2.dist-info/WHEEL
moadian2-0.0.2.dist-info/top_level.txt
moadian2-0.0.2.dist-info/RECORD
