Metadata-Version: 2.1
Name: moadian2
Version: 0.0.2
Summary: Connect to Moadian API V2
Author-email: Mojtaba Karimi <hi@thisiskarimi.com>
License: GNU GENERAL PUBLIC LICENSE
Project-URL: Homepage, https://github.com/thisiskarimi/moadian2
Project-URL: Issues, https://github.com/thisiskarimi/moadian2/issues
Keywords: moadian
Classifier: License :: OSI Approved :: MIT License
Classifier: Programming Language :: Python
Classifier: Programming Language :: Python :: 3
Classifier: Operating System :: OS Independent
Requires-Python: >=3.7
License-File: LICENSE
Requires-Dist: requests
Requires-Dist: Authlib
